ws_callbacks/__init__.py
ws_callbacks/tests/__init__.py
ws_callbacks-0.1.dist-info/DESCRIPTION.rst
ws_callbacks-0.1.dist-info/METADATA
ws_callbacks-0.1.dist-info/RECORD
ws_callbacks-0.1.dist-info/WHEEL
ws_callbacks-0.1.dist-info/metadata.json
ws_callbacks-0.1.dist-info/top_level.txt
