Metadata-Version: 2.0
Name: ws-callbacks
Version: 0.1
Summary: pattern for registering callbacks
Home-page: http://github.com/chuck1/web_sheets
Author: Charles Rymal
Author-email: charlesrymal@gmail.com
License: MIT
Platform: UNKNOWN
